yJSQL/JSQL.py
yJSQL/__init__.py
yJSQL/exceptions.py
yJSQL-0.1.3a0.dist-info/LICENSE
yJSQL-0.1.3a0.dist-info/METADATA
yJSQL-0.1.3a0.dist-info/WHEEL
yJSQL-0.1.3a0.dist-info/top_level.txt
yJSQL-0.1.3a0.dist-info/RECORD
